LICENSE
MANIFEST.in
README.md
setup.py
pyleafpro/__init__.py
pyleafpro/github_api.py
pyleafpro.egg-info/PKG-INFO
pyleafpro.egg-info/SOURCES.txt
pyleafpro.egg-info/dependency_links.txt
pyleafpro.egg-info/not-zip-safe
pyleafpro.egg-info/requires.txt
pyleafpro.egg-info/top_level.txt